turbo_seti/__init__.py
turbo_seti/drift_indexes/drift_indexes_array_10.txt
turbo_seti/drift_indexes/drift_indexes_array_11.txt
turbo_seti/drift_indexes/drift_indexes_array_2.txt
turbo_seti/drift_indexes/drift_indexes_array_3.txt
turbo_seti/drift_indexes/drift_indexes_array_4.txt
turbo_seti/drift_indexes/drift_indexes_array_5.txt
turbo_seti/drift_indexes/drift_indexes_array_6.txt
turbo_seti/drift_indexes/drift_indexes_array_7.txt
turbo_seti/drift_indexes/drift_indexes_array_8.txt
turbo_seti/drift_indexes/drift_indexes_array_9.txt
turbo_seti/find_doppler/__init__.py
turbo_seti/find_doppler/dat_diff.py
turbo_seti/find_doppler/data_handler.py
turbo_seti/find_doppler/file_writers.py
turbo_seti/find_doppler/find_doppler.py
turbo_seti/find_doppler/helper_functions.py
turbo_seti/find_doppler/merge_dats_logs.py
turbo_seti/find_doppler/seti_event.py
turbo_seti/find_doppler/turbo_seti_version.py
turbo_seti/find_doppler/kernels/__init__.py
turbo_seti/find_doppler/kernels/Scheduler/__init__.py
turbo_seti/find_doppler/kernels/_bitrev/__init__.py
turbo_seti/find_doppler/kernels/_hitsearch/__init__.py
turbo_seti/find_doppler/kernels/_hitsearch/kernels.cu
turbo_seti/find_doppler/kernels/_taylor_tree/__init__.py
turbo_seti/find_doppler/kernels/_taylor_tree/_core_cuda.py
turbo_seti/find_doppler/kernels/_taylor_tree/_core_numba.py
turbo_seti/find_event/__init__.py
turbo_seti/find_event/dat_filter.py
turbo_seti/find_event/find_event.py
turbo_seti/find_event/find_event_pipeline.py
turbo_seti/find_event/plot_dat.py
turbo_seti/find_event/plot_event.py
turbo_seti/find_event/plot_event_pipeline.py
turbo_seti/find_event/run_pipelines.py
turbo_seti-2.3.2.dist-info/LICENSE
turbo_seti-2.3.2.dist-info/METADATA
turbo_seti-2.3.2.dist-info/WHEEL
turbo_seti-2.3.2.dist-info/entry_points.txt
turbo_seti-2.3.2.dist-info/top_level.txt
turbo_seti-2.3.2.dist-info/RECORD
