Metadata-Version: 2.1
Name: turbo-seti
Version: 2.3.2
Summary: Analysis tool for the search of narrow band drifting signals in filterbank data
Home-page: https://github.com/UCBerkeleySETI/turbo_seti
Author: Emilio Enriquez
Author-email: e.enriquez@berkeley.edu
License: MIT License
Keywords: astronomy
Platform: UNKNOWN
Classifier: Development Status :: 4 - Beta
Classifier: Intended Audience :: Science/Research
Classifier: Programming Language :: Python :: 3
Classifier: Topic :: Scientific/Engineering
License-File: LICENSE
Requires-Dist: astropy
Requires-Dist: numpy
Requires-Dist: blimpy (>=2.0.34)
Requires-Dist: pandas
Requires-Dist: toolz
Requires-Dist: fsspec
Requires-Dist: dask
Requires-Dist: dask[bag]
Requires-Dist: numba
Requires-Dist: cloudpickle
